dataflake/wsgi/bjoern/__init__.py
dataflake/wsgi/bjoern/configurator.py
dataflake/wsgi/bjoern/skel/etc/site.zcml
dataflake/wsgi/bjoern/skel/etc/wsgi.conf.in
dataflake/wsgi/bjoern/skel/etc/zope.ini.in
dataflake/wsgi/bjoern/skel/var/README.txt
dataflake/wsgi/bjoern/skel/var/cache/README.txt
dataflake/wsgi/bjoern/skel/var/log/README.txt
dataflake/wsgi/bjoern/tests/__init__.py
dataflake/wsgi/bjoern/tests/test_bjoern_initialization.py
dataflake/wsgi/bjoern/tests/test_configbuilder.py
dataflake.wsgi.bjoern-2.2.dist-info/LICENSE.txt
dataflake.wsgi.bjoern-2.2.dist-info/METADATA
dataflake.wsgi.bjoern-2.2.dist-info/WHEEL
dataflake.wsgi.bjoern-2.2.dist-info/entry_points.txt
dataflake.wsgi.bjoern-2.2.dist-info/top_level.txt
dataflake.wsgi.bjoern-2.2.dist-info/RECORD
