Metadata-Version: 2.1
Name: dataflake.wsgi.bjoern
Version: 2.2
Summary: PasteDeploy entry point for the bjoern WSGI server
Home-page: https://github.com/dataflake/dataflake.wsgi.bjoern
Author: Jens Vagelpohl and Contributors
Author-email: jens@dataflake.org
License: ZPL 2.1
Project-URL: Documentation, https://dataflakewsgibjoern.readthedocs.io
Project-URL: Issue Tracker, https://github.com/dataflake/dataflake.wsgi.bjoern/issues
Project-URL: Sources, https://github.com/dataflake/dataflake.wsgi.bjoern
Classifier: Development Status :: 5 - Production/Stable
Classifier: Environment :: Web Environment
Classifier: Framework :: Zope
Classifier: Framework :: Zope :: 5
Classifier: Intended Audience :: System Administrators
Classifier: License :: OSI Approved :: Zope Public License
Classifier: Operating System :: OS Independent
Classifier: Programming Language :: Python
Classifier: Programming Language :: Python :: 3
Classifier: Programming Language :: Python :: 3.7
Classifier: Programming Language :: Python :: 3.8
Classifier: Programming Language :: Python :: 3.9
Classifier: Programming Language :: Python :: 3.10
Classifier: Programming Language :: Python :: 3.11
Classifier: Programming Language :: Python :: 3.12
Classifier: Programming Language :: Python :: Implementation :: CPython
Classifier: Topic :: Internet :: WWW/HTTP :: WSGI
Requires-Python: >=3.7
License-File: LICENSE.txt
Requires-Dist: setuptools
Requires-Dist: bjoern
Requires-Dist: paste
Requires-Dist: Zope >=5
Provides-Extra: docs
Requires-Dist: Sphinx ; extra == 'docs'
Requires-Dist: sphinx-rtd-theme ; extra == 'docs'
Requires-Dist: pkginfo ; extra == 'docs'
